kyosk/__init__.py
kyosk/__main__.py
kyosk/api/__init__.py
kyosk/api/controller/file_picker/file_picker_controller.py
kyosk/api/controller/file_picker/schema.py
kyosk/api/controller/task/schema.py
kyosk/api/controller/task/task_controller.py
kyosk/api/middleware.py
kyosk/api/routes/file_picker/__init__.py
kyosk/api/routes/health_check/__init__.py
kyosk/api/routes/task/__init__.py
kyosk/api/routes/types/__init__.py
kyosk/api/routes/workspace/__init__.py
kyosk/config.py
kyosk/domain/interface/sftp_client_interface.py
kyosk/domain/kyosk.py
kyosk/domain/media.py
kyosk/domain/sftp_credentials.py
kyosk/domain/task.py
kyosk/exception.py
kyosk/icon_bar.py
kyosk/service/colaborativo.py
kyosk/service/filePicker.py
kyosk/service/interface/autenticatitor_Interface.py
kyosk/service/interface/file_picker_interface.py
kyosk/service/sftp.py
kyosk/task/sftp_task.py
kyosk/user_case/kyosk_user_case.py
kyosk/user_case/task_user_case.py
kyosk/util.py
kyosk-0.1.2.dist-info/WHEEL
kyosk-0.1.2.dist-info/METADATA
kyosk-0.1.2.dist-info/RECORD
