Metadata-Version: 2.1
Name: kyosk
Version: 0.1.2
Summary: 
Author: rafaellobo
Author-email: rafaellobouezo@gmail.com
Requires-Python: >=3.6.1,<4.0.0
Classifier: Programming Language :: Python :: 3
Classifier: Programming Language :: Python :: 3.7
Classifier: Programming Language :: Python :: 3.8
Classifier: Programming Language :: Python :: 3.9
Requires-Dist: aiohttp (>=3.7.4,<4.0.0)
Requires-Dist: asyncio (>=3.4.3,<4.0.0)
Requires-Dist: asyncssh (>=2.6.0,<3.0.0)
Requires-Dist: fastapi (>=0.65.0,<0.66.0)
Requires-Dist: pydantic (>=1.8.1,<2.0.0)
Requires-Dist: pyinstaller (>=4.3,<5.0)
Requires-Dist: pynsist (>=2.7,<3.0)
Requires-Dist: pywin32 (>=300,<301)
Requires-Dist: ssh2-python (>=0.26.0,<0.27.0)
Requires-Dist: tzlocal (>=2.1,<3.0)
Requires-Dist: uvicorn (>=0.13.4,<0.14.0)
